Agent/AgentKeywords.py
Agent/__init__.py
Agent/_test_listener.py
Agent/agent_engine.py
Agent/ai/__init__.py
Agent/ai/_promptcomposer.py
Agent/ai/llm/__init__.py
Agent/ai/llm/_anthropic.py
Agent/ai/llm/_baseclient.py
Agent/ai/llm/_converters.py
Agent/ai/llm/_factory.py
Agent/ai/llm/_gemini.py
Agent/ai/llm/_openaiclient.py
Agent/ai/llm/facade.py
Agent/ai/prompts/__init__.py
Agent/ai/vlm/__init__.py
Agent/ai/vlm/_client.py
Agent/ai/vlm/_parser.py
Agent/ai/vlm/_selector.py
Agent/ai/vlm/interface.py
Agent/config/__init__.py
Agent/config/config.py
Agent/config/llm_models.json
Agent/config/model_config.py
Agent/core/__init__.py
Agent/core/interfaces.py
Agent/core/keyword_runner.py
Agent/platforms/__init__.py
Agent/platforms/_mobileconnector.py
Agent/platforms/_platformfactory.py
Agent/platforms/collectors/__init__.py
Agent/platforms/collectors/android_collector.py
Agent/platforms/collectors/ios_collector.py
Agent/platforms/filters/__init__.py
Agent/platforms/filters/pipeline.py
Agent/platforms/filters/android/__init__.py
Agent/platforms/filters/android/bounds.py
Agent/platforms/filters/android/container.py
Agent/platforms/filters/android/displayed.py
Agent/platforms/filters/android/interactive.py
Agent/platforms/filters/android/smart_hierarchy.py
Agent/platforms/grounding/__init__.py
Agent/platforms/grounding/composer.py
Agent/platforms/grounding/som/__init__.py
Agent/platforms/grounding/som/annotator.py
Agent/platforms/grounding/som/serializer.py
Agent/platforms/grounding/text/__init__.py
Agent/platforms/grounding/text/serializer.py
Agent/platforms/locators/__init__.py
Agent/platforms/locators/android_locator.py
Agent/platforms/locators/ios_locator.py
Agent/platforms/locators/mobile_locator.py
Agent/tools/__init__.py
Agent/tools/base.py
Agent/tools/registry.py
Agent/tools/mobile/__init__.py
Agent/tools/mobile/click_element.py
Agent/tools/mobile/go_back.py
Agent/tools/mobile/hide_keyboard.py
Agent/tools/mobile/input_text.py
Agent/tools/mobile/long_press.py
robotframework_agent-0.0.2.dist-info/licenses/LICENSE
robotframework_agent-0.0.2.dist-info/METADATA
robotframework_agent-0.0.2.dist-info/WHEEL
robotframework_agent-0.0.2.dist-info/top_level.txt
robotframework_agent-0.0.2.dist-info/RECORD
