Metadata-Version: 2.4
Name: robotframework-agent
Version: 0.0.2
Summary: AI-driven test automation agent for apps
Author-email: Abdelkader HASSINE <contact.abdelkaderhassine@gmail.com>, Pavlo Ivashchenko <pawloiwanov@gmail.com>
License: CC0-1.0
Project-URL: Homepage, https://github.com/aidriventesting
Project-URL: Documentation, https://github.com/aidriventesting/agent#readme
Project-URL: Repository, https://github.com/aidriventesting/agent
Project-URL: Issues, https://github.com/aidriventesting/agent/issues
Keywords: robotframework,ai,automation,automation agent,llm,testing
Classifier: Development Status :: 3 - Alpha
Classifier: Intended Audience :: Developers
Classifier: Topic :: Software Development :: Testing
Classifier: License :: CC0 1.0 Universal (CC0 1.0) Public Domain Dedication
Classifier: Programming Language :: Python :: 3
Classifier: Programming Language :: Python :: 3.10
Classifier: Programming Language :: Python :: 3.11
Classifier: Programming Language :: Python :: 3.12
Classifier: Programming Language :: Python :: 3.13
Classifier: Framework :: Robot Framework
Classifier: Framework :: Robot Framework :: Library
Requires-Python: >=3.10
License-File: LICENSE
Requires-Dist: robotframework>=6.0
Requires-Dist: openai>=1.0.0
Requires-Dist: Pillow>=10.0.0
Requires-Dist: tiktoken>=0.5.0
Requires-Dist: python-dotenv>=1.0.0
Requires-Dist: requests>=2.31.0
Provides-Extra: web
Requires-Dist: playwright>=1.40.0; extra == "web"
Provides-Extra: mobile
Requires-Dist: robotframework-appiumlibrary>=3.0; extra == "mobile"
Requires-Dist: Appium-Python-Client>=5.0; extra == "mobile"
Provides-Extra: test
Requires-Dist: pytest>=8.0.0; extra == "test"
Requires-Dist: pytest-cov>=4.1.0; extra == "test"
Provides-Extra: dev
Requires-Dist: playwright>=1.40.0; extra == "dev"
Requires-Dist: robotframework-appiumlibrary>=3.0; extra == "dev"
Requires-Dist: Appium-Python-Client>=5.0; extra == "dev"
Requires-Dist: pytest>=8.0.0; extra == "dev"
Requires-Dist: pytest-cov>=4.1.0; extra == "dev"
Requires-Dist: pytest-xdist>=3.5.0; extra == "dev"
Requires-Dist: black>=24.0.0; extra == "dev"
Requires-Dist: flake8>=7.0.0; extra == "dev"
Requires-Dist: mypy>=1.8.0; extra == "dev"
Requires-Dist: isort>=5.13.0; extra == "dev"
Requires-Dist: pre-commit>=3.6.0; extra == "dev"
Requires-Dist: anthropic>=0.20.0; extra == "dev"
Requires-Dist: google-generativeai>=0.3.0; extra == "dev"
Requires-Dist: gradio-client>=2.0.0; extra == "dev"
Provides-Extra: browserstack
Requires-Dist: browserstack-sdk>=1.30.0; extra == "browserstack"
Requires-Dist: browserstack-local>=1.2.0; extra == "browserstack"
Provides-Extra: anthropic
Requires-Dist: anthropic>=0.20.0; extra == "anthropic"
Provides-Extra: gemini
Requires-Dist: google-generativeai>=0.3.0; extra == "gemini"
Provides-Extra: vision
Requires-Dist: gradio-client>=2.0.0; extra == "vision"
Dynamic: license-file
